Workbook

Sheet Data
A1: Order ID | B1: Date | C1: Region | D1: Category | E1: Product | F1: Salesperson | G1: Quantity | H1: Unit Price | I1: Discount | J1: Unit Cost | K1: Revenue | L1: Profit | M1: Margin
A2: ORD-00001 | B2: 46186 | C2: Southeast | D2: Accessories | E2: USB-C Hub | F2: Elisa | G2: 4 | H2: 67.85 | I2: 0 | J2: 32.55 | K2: =G2*H2*(1-I2) -> 271.4 | L2: =K2-(G2*J2) -> 141.2 | M2: =IFERROR(L2/K2,0) -> 0.52026529
A3: ORD-00002 | B3: 46045 | C3: Northeast | D3: Technology | E3: Laptop Pro | F3: Bruno | G3: 2 | H3: 1206.58 | I3: 0 | J3: 834.13 | K3: =G3*H3*(1-I3) -> 2413.16 | L3: =K3-(G3*J3) -> 744.9 | M3: =IFERROR(L3/K3,0) -> 0.30868239
A4: ORD-00003 | B4: 46206 | C4: Northeast | D4: Home | E4: Air Purifier | F4: Bruno | G4: 8 | H4: 185.91 | I4: 0.05 | J4: 107.84 | K4: =G4*H4*(1-I4) -> 1412.916 | L4: =K4-(G4*J4) -> 550.196 | M4: =IFERROR(L4/K4,0) -> 0.38940461
A5: ORD-00004 | B5: 46201 | C5: South | D5: Accessories | E5: USB-C Hub | F5: Ana | G5: 4 | H5: 69.32 | I5: 0.2 | J5: 31.51 | K5: =G5*H5*(1-I5) -> 221.824 | L5: =K5-(G5*J5) -> 95.784 | M5: =IFERROR(L5/K5,0) -> 0.43180179
A6: ORD-00005 | B6: 46114 | C6: Midwest | D6: Accessories | E6: USB-C Hub | F6: Elisa | G6: 8 | H6: 73.33 | I6: 0.05 | J6: 31.97 | K6: =G6*H6*(1-I6) -> 557.308 | L6: =K6-(G6*J6) -> 301.548 | M6: =IFERROR(L6/K6,0) -> 0.54107962
A7: ORD-00006 | B7: 46098 | C7: Midwest | D7: Accessories | E7: Webcam HD | F7: Carla | G7: 4 | H7: 91.59 | I7: 0.1 | J7: 47.59 | K7: =G7*H7*(1-I7) -> 329.724 | L7: =K7-(G7*J7) -> 139.364 | M7: =IFERROR(L7/K7,0) -> 0.42266866
A8: ORD-00007 | B8: 46043 | C8: Midwest | D8: Technology | E8: Wireless Mouse | F8: Carla | G8: 5 | H8: 36.23 | I8: 0.05 | J8: 15.81 | K8: =G8*H8*(1-I8) -> 172.0925 | L8: =K8-(G8*J8) -> 93.0425 | M8: =IFERROR(L8/K8,0) -> 0.54065401
A9: ORD-00008 | B9: 46076 | C9: Northeast | D9: Technology | E9: Monitor 27 | F9: Carla | G9: 3 | H9: 284.79 | I9: 0.05 | J9: 180.56 | K9: =G9*H9*(1-I9) -> 811.6515 | L9: =K9-(G9*J9) -> 269.9715 | M9: =IFERROR(L9/K9,0) -> 0.33261997
A10: ORD-00009 | B10: 46259 | C10: Northeast | D10: Office | E10: Desk Lamp | F10: Ana | G10: 6 | H10: 56.64 | I10: 0.15 | J10: 23.79 | K10: =G10*H10*(1-I10) -> 288.864 | L10: =K10-(G10*J10) -> 146.124 | M10: =IFERROR(L10/K10,0) -> 0.50585743
A11: ORD-00010 | B11: 46229 | C11: Southeast | D11: Accessories | E11: USB-C Hub | F11: Bruno | G11: 4 | H11: 70.77 | I11: 0.15 | J11: 32.51 | K11: =G11*H11*(1-I11) -> 240.618 | L11: =K11-(G11*J11) -> 110.578 | M11: =IFERROR(L11/K11,0) -> 0.4595583
A12: ORD-00011 | B12: 46190 | C12: South | D12: Home | E12: Air Purifier | F12: Felipe | G12: 5 | H12: 184.87 | I12: 0 | J12: 110.76 | K12: =G12*H12*(1-I12) -> 924.35 | L12: =K12-(G12*J12) -> 370.55 | M12: =IFERROR(L12/K12,0) -> 0.40087629
A13: ORD-00012 | B13: 46172 | C13: South | D13: Home | E13: Coffee Maker | F13: Ana | G13: 4 | H13: 121.56 | I13: 0.2 | J13: 72.34 | K13: =G13*H13*(1-I13) -> 388.992 | L13: =K13-(G13*J13) -> 99.632 | M13: =IFERROR(L13/K13,0) -> 0.25612866
... A501: ORD-00500 | B501: 46154 | C501: Northeast | D501: Office | E501: Office Chair | F501: Felipe | G501: 3 | H501: 223.12 | I501: 0 | J501: 132.71 | K501: =G501*H501*(1-I501) -> 669.36 | L501: =K501-(G501*J501) -> 271.23 | M501: =IFERROR(L501/K501,0) -> 0.40520796

Sheet Dashboard
A1: SALES PERFORMANCE DASHBOARD
A3: Portfolio Demo • Excel Dashboard • KPIs • Business Insights
A4: TOTAL REVENUE | D4: TOTAL PROFIT | G4: PROFIT MARGIN | J4: ORDERS
A5: =SUM(Data!$K$2:$K$501) -> 468702.52 | D5: =SUM(Data!$L$2:$L$501) -> 156299.97 | G5: =IFERROR(SUM(Data!$L$2:$L$501)/SUM(Data!$K$2:$K$501),0) -> 0.33347371 | J5: =COUNTA(Data!$A$2:$A$501) -> 500
G24: BUSINESS INSIGHTS
G25: • Identify months with stronger or weaker sales performance. • Compare categories by revenue and profit. • Review regional performance to support sales decisions. • Use the Data sheet filters to investigate products and salespeople. Portfolio tip: replace this text with 3–5 insights you discover yourself.

Sheet Summary
A1: Month | B1: Revenue | C1: Profit | E1: Category | F1: Revenue | G1: Profit | I1: Region | J1: Revenue | K1: Profit
A2: 46023 | B2: =SUMIFS(Data!$K$2:$K$501,Data!$B$2:$B$501,">="&A2,Data!$B$2:$B$501,"<"&A3) -> 91909.093 | C2: =SUMIFS(Data!$L$2:$L$501,Data!$B$2:$B$501,">="&A2,Data!$B$2:$B$501,"<"&A3) -> 27950.532 | E2: Technology | F2: =SUMIFS(Data!$K$2:$K$501,Data!$D$2:$D$501,E2) -> 241046.05 | G2: =SUMIFS(Data!$L$2:$L$501,Data!$D$2:$D$501,E2) -> 67199.959 | I2: Southeast | J2: =SUMIFS(Data!$K$2:$K$501,Data!$C$2:$C$501,I2) -> 201858.73 | K2: =SUMIFS(Data!$L$2:$L$501,Data!$C$2:$C$501,I2) -> 65599.452
A3: 46054 | B3: =SUMIFS(Data!$K$2:$K$501,Data!$B$2:$B$501,">="&A3,Data!$B$2:$B$501,"<"&A4) -> 37370.415 | C3: =SUMIFS(Data!$L$2:$L$501,Data!$B$2:$B$501,">="&A3,Data!$B$2:$B$501,"<"&A4) -> 14372.015 | E3: Office | F3: =SUMIFS(Data!$K$2:$K$501,Data!$D$2:$D$501,E3) -> 116778.82 | G3: =SUMIFS(Data!$L$2:$L$501,Data!$D$2:$D$501,E3) -> 41662.757 | I3: South | J3: =SUMIFS(Data!$K$2:$K$501,Data!$C$2:$C$501,I3) -> 81240.724 | K3: =SUMIFS(Data!$L$2:$L$501,Data!$C$2:$C$501,I3) -> 29553.004
A4: 46082 | B4: =SUMIFS(Data!$K$2:$K$501,Data!$B$2:$B$501,">="&A4,Data!$B$2:$B$501,"<"&A5) -> 60067.707 | C4: =SUMIFS(Data!$L$2:$L$501,Data!$B$2:$B$501,">="&A4,Data!$B$2:$B$501,"<"&A5) -> 19514.017 | E4: Accessories | F4: =SUMIFS(Data!$K$2:$K$501,Data!$D$2:$D$501,E4) -> 46822.764 | G4: =SUMIFS(Data!$L$2:$L$501,Data!$D$2:$D$501,E4) -> 22483.494 | I4: Northeast | J4: =SUMIFS(Data!$K$2:$K$501,Data!$C$2:$C$501,I4) -> 86070.775 | K4: =SUMIFS(Data!$L$2:$L$501,Data!$C$2:$C$501,I4) -> 27336.715
A5: 46113 | B5: =SUMIFS(Data!$K$2:$K$501,Data!$B$2:$B$501,">="&A5,Data!$B$2:$B$501,"<"&A6) -> 56070.831 | C5: =SUMIFS(Data!$L$2:$L$501,Data!$B$2:$B$501,">="&A5,Data!$B$2:$B$501,"<"&A6) -> 19377.93 | E5: Home | F5: =SUMIFS(Data!$K$2:$K$501,Data!$D$2:$D$501,E5) -> 64054.888 | G5: =SUMIFS(Data!$L$2:$L$501,Data!$D$2:$D$501,E5) -> 24953.758 | I5: Midwest | J5: =SUMIFS(Data!$K$2:$K$501,Data!$C$2:$C$501,I5) -> 56825.175 | K5: =SUMIFS(Data!$L$2:$L$501,Data!$C$2:$C$501,I5) -> 18643.076
A6: 46143 | B6: =SUMIFS(Data!$K$2:$K$501,Data!$B$2:$B$501,">="&A6,Data!$B$2:$B$501,"<"&A7) -> 38260.512 | C6: =SUMIFS(Data!$L$2:$L$501,Data!$B$2:$B$501,">="&A6,Data!$B$2:$B$501,"<"&A7) -> 13247.323 | I6: North | J6: =SUMIFS(Data!$K$2:$K$501,Data!$C$2:$C$501,I6) -> 42707.112 | K6: =SUMIFS(Data!$L$2:$L$501,Data!$C$2:$C$501,I6) -> 15167.722
A7: 46174 | B7: =SUMIFS(Data!$K$2:$K$501,Data!$B$2:$B$501,">="&A7,Data!$B$2:$B$501,"<"&A8) -> 54774.685 | C7: =SUMIFS(Data!$L$2:$L$501,Data!$B$2:$B$501,">="&A7,Data!$B$2:$B$501,"<"&A8) -> 18706.285
A8: 46204 | B8: =SUMIFS(Data!$K$2:$K$501,Data!$B$2:$B$501,">="&A8,Data!$B$2:$B$501,"<"&A9) -> 61062.387 | C8: =SUMIFS(Data!$L$2:$L$501,Data!$B$2:$B$501,">="&A8,Data!$B$2:$B$501,"<"&A9) -> 19373.597
A9: 46235 | B9: =SUMIFS(Data!$K$2:$K$501,Data!$B$2:$B$501,">="&A9,Data!$B$2:$B$501,"<"&DATE(2026,9,1)) -> 69186.887 | C9: =SUMIFS(Data!$L$2:$L$501,Data!$B$2:$B$501,">="&A9,Data!$B$2:$B$501,"<"&DATE(2026,9,1)) -> 23758.267
